{
    "jobs": [
      {
        "id": 1,
        "job": "Front End Developer",
        "company": "TCS",
        "image": "https://upload.wikimedia.org/wikipedia/commons/thumb/b/b1/Tata_Consultancy_Services_Logo.svg/768px-Tata_Consultancy_Services_Logo.svg.png",
        "address": "Phase 3, Hinjewadi Rajiv Gandhi Infotech Park, Hinjawadi, Maharashtra 411057",
        "position": "12",
        "h1": "HTML/CSS",
        "t2": "javascript",
        "t3": "React js/Angular js",
        "p1": "In-depth understanding of the entire web development process (design, development and deployment)",
        "p3": "Use markup languages like HTML to create user-friendly web pages",
        "p2": "Maintain and improve website",
        "p4": "Ensure high quality graphic standards and brand consistency",
        "r1": "Proven work experience as a Front-end developer",
        "r2": "Collaborate with back-end developers and web designers to improve usability",
        "r3": "Stay up-to-date on emerging technologies"
      },
      {
        "id": 2,
        "job": "Back End Developer",
        "company": "Infosys",
        "image": "https://cdn-ukwest.onetrust.com/logos/8d84415b-1b52-4bc4-8d5f-ca9a8eccaf8a/f7db8968-fc22-4620-92ac-dc05c5d2aa15/02460a41-565e-4cac-80a7-449bc8f77a72/logo-infosys.png",
        "address": "Phase 3, Hinjewadi Rajiv Gandhi Infotech Park, Hinjawadi, Maharashtra 411057",
        "position": "12",
        "h1": "Node js",
        "t2": "Express js",
        "t3": "Mongodb/Mysql",
     
        "p1": "In-depth understanding of the entire web development process (design, development and deployment)",
        "p3": "Use markup languages like HTML to create user-friendly web pages",
        "p2": "Maintain and improve website",
        "p4": "Ensure high quality graphic standards and brand consistency",
        "r1": "Proven work experience as a Front-end developer",
        "r2": "Collaborate with back-end developers and web designers to improve usability",
        "r3": "Stay up-to-date on emerging technologies"
      },
      {
        "id": 3,
        "job": "PHP Developer",
        "company": "Accenture",
        "image": "https://1000logos.net/wp-content/uploads/2021/04/Accenture-logo.png",
        "address": "Phase 3, Hinjewadi Rajiv Gandhi Infotech Park, Hinjawadi, Maharashtra 411057",
        "position": "12",
        "h1": "Node js",
        "t2": "Express js",
        "t3": "Mongodb/Mysql",
        "p1": "In-depth understanding of the entire web development process (design, development and deployment)",
        "p3": "Use markup languages like HTML to create user-friendly web pages",
        "p2": "Maintain and improve website",
        "p4": "Ensure high quality graphic standards and brand consistency",
        "r1": "Proven work experience as a Front-end developer",
        "r2": "Collaborate with back-end developers and web designers to improve usability",
        "r3": "Stay up-to-date on emerging technologies"
      },
      {
        "id": 4,
        "job": "Data Analytics",
        "company": "Cognizant",
        "image": "https://1000logos.net/wp-content/uploads/2021/09/Cognizant-Logo.jpg",
        "address": "Phase 3, Hinjewadi Rajiv Gandhi Infotech Park, Hinjawadi, Maharashtra 411057",
        "position": "12",
        "h1": "Python ",
        "t2": "Numpy",
        "t3": "Pandas",
        "p1": "In-depth understanding of the entire web development process (design, development and deployment)",
        "p3": "Use markup languages like HTML to create user-friendly web pages",
        "p2": "Maintain and improve website",
        "p4": "Ensure high quality graphic standards and brand consistency",
        "r1": "Proven work experience as a Front-end developer",
        "r2": "Collaborate with back-end developers and web designers to improve usability",
        "r3": "Stay up-to-date on emerging technologies"
      },
      {
        "id": 5,
        "job": "SQL Developer",
        "company": "Wipro",
        "image": "https://upload.wikimedia.org/wikipedia/commons/thumb/a/a0/Wipro_Primary_Logo_Color_RGB.svg/220px-Wipro_Primary_Logo_Color_RGB.svg.png",
        "address": "Phase 3, Hinjewadi Rajiv Gandhi Infotech Park, Hinjawadi, Maharashtra 411057",
        "position": "12",
        "h1": "Laravel",
        "t2": "Oracal",
        "t3": "MySql",
        "p1": "In-depth understanding of the entire web development process (design, development and deployment)",
        "p3": "Use markup languages like HTML to create user-friendly web pages",
        "p2": "Maintain and improve website",
        "p4": "Ensure high quality graphic standards and brand consistency",
        "r1": "Proven work experience as a Front-end developer",
        "r2": "Collaborate with back-end developers and web designers to improve usability",
        "r3": "Stay up-to-date on emerging technologies"
      },
      {
        "id": 6,
        "job": "UI/UX Designer",
        "company": "Tech Mahindra",
        "image": "https://bl-i.thgim.com/public/info-tech/4d6e6d/article31192849.ece/alternates/FREE_1200/Tech-mahindra-temporary-logo-covid19jpg",
        "address": "Phase 3, Hinjewadi Rajiv Gandhi Infotech Park, Hinjawadi, Maharashtra 411057",
        "position": "12",
        "h1": "Figma",
        "t2": "PhotoShop",
        "t3": "Cad",
        "p1": "In-depth understanding of the entire web development process (design, development and deployment)",
        "p3": "Use markup languages like HTML to create user-friendly web pages",
        "p2": "Maintain and improve website",
        "p4": "Ensure high quality graphic standards and brand consistency",
        "r1": "Proven work experience as a Front-end developer",
        "r2": "Collaborate with back-end developers and web designers to improve usability",
        "r3": "Stay up-to-date on emerging technologies"
      }
    ]
  }
  
  